nonebot_plugin_bilicover/__init__.py
nonebot_plugin_bilicover-0.2.2.dist-info/WHEEL
nonebot_plugin_bilicover-0.2.2.dist-info/METADATA
nonebot_plugin_bilicover-0.2.2.dist-info/licenses/LICENSE
nonebot_plugin_bilicover-0.2.2.dist-info/RECORD
