Metadata-Version: 2.1
Name: nonebot-plugin-bilicover
Version: 0.2.2
Summary: A plugin to get the bilibili video cover for NoneBot2
License: MIT
Author-email: Akirami <Akiramiaya@outlook.com>
Requires-Python: >=3.8
Requires-Dist: httpx>=0.23.1
Requires-Dist: nonebot-adapter-onebot>=2.0.0b1
Requires-Dist: nonebot2>=2.0.0b2
Project-URL: Homepage, https://github.com/A-kirami/nonebot-plugin-bilicover
Project-URL: Repository, https://github.com/A-kirami/nonebot-plugin-bilicover
